vdeh/__init__.py
vdeh/main.py
vdeh/docs/index.html
vdeh/example data/050922BaSH.csv
vdeh/example data/052322BaSH.csv
vdeh/example data/053022BaSH.csv
vdeh/gui/__init__.py
vdeh/gui/animal_metadata_form.ui
vdeh/gui/column_names_form.ui
vdeh/gui/derived_data_form.ui
vdeh/gui/model_form.ui
vdeh/gui/timepoint_data_form.ui
vdeh/gui/vdeh_controller.py
vdeh/gui/vdeh_form.ui
vdeh/gui/vdeh_form_lite.ui
vdeh/gui/vdeh_model.py
vdeh/gui/vdeh_subgui_controller.py
vdeh/gui/vdeh_tests.py
vdeh-5.4.5.dist-info/METADATA
vdeh-5.4.5.dist-info/WHEEL
vdeh-5.4.5.dist-info/licenses/LICENSE
vdeh-5.4.5.dist-info/RECORD
