Metadata-Version: 2.4
Name: vdeh
Version: 5.4.5
Project-URL: Repository, https://github.com/realchrisward/VevoLab_Data_Extraction_Helper
Maintainer-email: Chris Ward <ward.chris.s@gmail.com>
License: MIT License
License-File: LICENSE
Keywords: Echocardiography,VevoLab,VisualSonics
Classifier: Development Status :: 3 - Alpha
Classifier: Programming Language :: Python
Requires-Python: >=3.13
Requires-Dist: numpy>=2.2.5
Requires-Dist: pandas>=2.2.3
Requires-Dist: pingouin
Requires-Dist: pyside6>=6.9.0
Requires-Dist: scipy>=1.15.2
Requires-Dist: seaborn
Requires-Dist: statsmodels
Requires-Dist: xlrd
Requires-Dist: xlsxwriter
Requires-Dist: xlwt
